{"name":"GitHub","postlist":[{"title":"GitHub Archive Program,我的祖传代码","slug":"GitHub-Archive-Program-我的祖传代码","date":"2020-07-18T09:22:54.000Z","updated":"2023-11-06T14:15:17.978Z","comments":true,"path":"api/articles/GitHub-Archive-Program-我的祖传代码.json","excerpt":null,"keywords":null,"cover":"https://cdn.jsdelivr.net/gh/gentlemanhu/public-store/images/20200718172658.png","content":null,"raw":null,"categories":[{"name":"日常杂记","path":"api/categories/日常杂记.json"},{"name":"随手记","path":"api/categories/随手记.json"}],"tags":[{"name":"GitHub","path":"api/tags/GitHub.json"},{"name":"祖传代码","path":"api/tags/祖传代码.json"}]},{"title":"git submodule git子模块闲搞","slug":"git-submodule-git子模块闲搞","date":"2020-07-21T10:58:35.000Z","updated":"2023-11-06T14:15:17.983Z","comments":true,"path":"api/articles/git-submodule-git子模块闲搞.json","excerpt":null,"keywords":null,"cover":"https://cdn.jsdelivr.net/gh/gentlemanhu/public-store/images/sunset-174276_1920.jpg","content":null,"raw":null,"categories":[{"name":"编程杂记","path":"api/categories/编程杂记.json"},{"name":"Linux","path":"api/categories/Linux.json"},{"name":"Git","path":"api/categories/Git.json"}],"tags":[{"name":"GitHub","path":"api/tags/GitHub.json"},{"name":"Git","path":"api/tags/Git.json"},{"name":"博客","path":"api/tags/博客.json"},{"name":"Git submodule","path":"api/tags/Git submodule.json"}]}]}