{"name":"引导","postlist":[{"title":"Clover配置引导Linux内核","slug":"Clover配置引导Linux内核","date":"2020-08-12T07:11:07.000Z","updated":"2023-11-06T14:15:17.978Z","comments":true,"path":"api/articles/Clover配置引导Linux内核.json","excerpt":null,"keywords":null,"cover":"https://cdn.jsdelivr.net/gh/gentlemanhu/public-store/images/20200820200255.png","content":null,"raw":null,"categories":[{"name":"玩玩","path":"api/categories/玩玩.json"},{"name":"黑苹果","path":"api/categories/黑苹果.json"}],"tags":[{"name":"黑苹果","path":"api/tags/黑苹果.json"},{"name":"Clover","path":"api/tags/Clover.json"},{"name":"Manjaro","path":"api/tags/Manjaro.json"},{"name":"引导","path":"api/tags/引导.json"}]}]}